{"title": "Exact Recovery of Sparse-Used Dictionaries.", "fields": ["convolution", "second generation wavelet transform", "digital holography", "deconvolution", "sampling", "backus gilbert method", "fast wavelet transform", "matching pursuit", "sparse approximation", "regularization perspectives on support vector machines", "wavelet packet decomposition", "determining the number ", "maxima and minima", "compressed sensing", "tikhonov regularization", "matlab", "parameterized complexity", "invertible matrix", "stationary wavelet transform", "coherence", "restricted isometry property", "feature learning", "well posed problem", "matrix", "instant", "license", "rate ", "convex optimization", "lifting scheme", "machine learning", "k svd", "observability", "benchmarking", "cluster analysis", "sparse matrix", "software"], "abstract": "Complete Dictionary ", "citation": "Citations (63)", "year": "2013", "departments": ["Columbia University", "Columbia University", "Columbia University", "Johns Hopkins University", "Johns Hopkins University", "Johns Hopkins University", "Duke University", "Duke University", "Duke University", "University of Minnesota", "Duke University", "\u00c9cole sup\u00e9rieure de chimie physique \u00e9lectronique de Lyon", "University of Lyon", "Braunschweig University of Technology", "University of Bremen", "Braunschweig University of Technology", "University of Bremen", "University of Bremen", "Massachusetts Institute of Technology", "Massachusetts Institute of Technology", "SAGEM", "SAGEM", "University of British", "University of British", "University of British", "University of British", "University of British", "ICS-FORTH, Heraklion, Greece", "ICS-FORTH, Heraklion, Greece", "Service d'Astro ... -Yvette, France"], "conf": "ijcai", "authors": ["Huan Wang.....http://dblp.org/pers/hd/w/Wang:Huan", "Daniel A. Spielman.....http://dblp.org/pers/hd/s/Spielman:Daniel_A=", "John Wright.....http://dblp.org/pers/hd/w/Wright:John"], "pages": 4}