{"title": "CAGAN: Consistent Adversarial Training Enhanced GANs.", "fields": ["machine learning", "computer science", "artificial intelligence", "adversarial system"], "abstract": null, "citation": "Not cited", "year": "2018", "departments": ["Beijing Institute of Technology", "Beijing Institute of Technology", "Beijing Institute of Technology", "Beijing Institute of Technology", "Beijing Institute of Technology"], "conf": "ijcai", "authors": ["Yao Ni.....http://dblp.org/pers/hd/n/Ni:Yao", "Dandan Song.....http://dblp.org/pers/hd/s/Song:Dandan", "Xi Zhang.....http://dblp.org/pers/hd/z/Zhang:Xi", "Hao Wu.....http://dblp.org/pers/hd/w/Wu:Hao", "Lejian Liao.....http://dblp.org/pers/hd/l/Liao:Lejian"], "pages": 7}