{"title": "How to identify global trends from local decisions? Event region detection on mobile networks.", "fields": ["machine learning", "computer science", "artificial intelligence", "theoretical computer science"], "abstract": null, "citation": "Citations (14)", "year": "2014", "departments": ["Delft University of Technology", "Delft University of Technology", "Delft University of Technology", "Stony Brook University"], "conf": "infocom", "authors": ["Andreas Loukas.....http://dblp.org/pers/hd/l/Loukas:Andreas", "Marco Zuniga.....http://dblp.org/pers/hd/z/Zuniga:Marco", "Ioannis Protonotarios.....http://dblp.org/pers/hd/p/Protonotarios:Ioannis", "Jie Gao.....http://dblp.org/pers/hd/g/Gao:Jie"], "pages": 9}