{"title": "Is it worth to be patient? Analysis and optimization of delayed mobile data offloading.", "fields": ["computer network", "distributed computing", "mobile data offloading", "computer science"], "abstract": null, "citation": "Citations (80)", "year": "2014", "departments": ["Institut Eur\u00e9com", "Institut Eur\u00e9com"], "conf": "infocom", "authors": ["Fidan Mehmeti.....http://dblp.org/pers/hd/m/Mehmeti:Fidan", "Thrasyvoulos Spyropoulos.....http://dblp.org/pers/hd/s/Spyropoulos:Thrasyvoulos"], "pages": 9}