{"title": "Structured Variationally Auto-encoded Optimization.", "fields": ["pattern recognition", "computer science", "artificial intelligence", "machine learning"], "abstract": null, "citation": "Not cited", "year": "2018", "departments": ["University of Oxford", "Amazon.com", "Amazon.com", "Amazon.com"], "conf": "icml", "authors": ["Xiaoyu Lu.....http://dblp.org/pers/hd/l/Lu:Xiaoyu", "Javier Gonzalez.....http://dblp.org/pers/hd/g/Gonzalez:Javier", "Zhenwen Dai.....http://dblp.org/pers/hd/d/Dai:Zhenwen", "Neil D. Lawrence.....http://dblp.org/pers/hd/l/Lawrence:Neil_D="], "pages": 9}